jitxlib/bundles/__init__.py
jitxlib/bundles/gates.py
jitxlib/circuits/__init__.py
jitxlib/circuits/pool.py
jitxlib/geometry/linerectangle.py
jitxlib/landpatterns/__init__.py
jitxlib/landpatterns/courtyard.py
jitxlib/landpatterns/dual.py
jitxlib/landpatterns/grid_layout.py
jitxlib/landpatterns/grid_planner.py
jitxlib/landpatterns/ipc.py
jitxlib/landpatterns/keepout.py
jitxlib/landpatterns/package.py
jitxlib/landpatterns/pads.py
jitxlib/landpatterns/quad.py
jitxlib/landpatterns/generators/__init__.py
jitxlib/landpatterns/generators/bga.py
jitxlib/landpatterns/generators/header.py
jitxlib/landpatterns/generators/qfn.py
jitxlib/landpatterns/generators/qfp.py
jitxlib/landpatterns/generators/soic.py
jitxlib/landpatterns/generators/son.py
jitxlib/landpatterns/generators/sop.py
jitxlib/landpatterns/generators/sot.py
jitxlib/landpatterns/leads/__init__.py
jitxlib/landpatterns/leads/fillets.py
jitxlib/landpatterns/leads/lead-fillets-table.csv
jitxlib/landpatterns/leads/protrusion.py
jitxlib/landpatterns/leads/protrusions.py
jitxlib/landpatterns/silkscreen/__init__.py
jitxlib/landpatterns/silkscreen/labels.py
jitxlib/landpatterns/silkscreen/marker.py
jitxlib/landpatterns/silkscreen/outlines.py
jitxlib/landpatterns/twopin/SMT_table.py
jitxlib/landpatterns/twopin/axial.py
jitxlib/landpatterns/twopin/molded.py
jitxlib/landpatterns/twopin/radial.py
jitxlib/landpatterns/twopin/smt.py
jitxlib/physics/__init__.py
jitxlib/protocols/__init__.py
jitxlib/protocols/displayport.py
jitxlib/protocols/serial.py
jitxlib/protocols/usb.py
jitxlib/protocols/ethernet/__init__.py
jitxlib/protocols/ethernet/mdi/e10gbase_kr.py
jitxlib/protocols/ethernet/mdi/mdi1000base_t.py
jitxlib/protocols/ethernet/mdi/mdi100base_tx.py
jitxlib/protocols/ethernet/mii/gmii.py
jitxlib/protocols/ethernet/mii/mii.py
jitxlib/protocols/ethernet/mii/miim.py
jitxlib/protocols/ethernet/mii/rgmii.py
jitxlib/protocols/ethernet/mii/rmii.py
jitxlib/symbols/__init__.py
jitxlib/symbols/arrow.py
jitxlib/symbols/box.py
jitxlib_standard-4.0.1.dist-info/METADATA
jitxlib_standard-4.0.1.dist-info/WHEEL
jitxlib_standard-4.0.1.dist-info/RECORD
