Metadata-Version: 2.4
Name: jitxlib-standard
Version: 4.0.1
Summary: JITX Standard Library
Project-URL: Homepage, https://jitx.com
Project-URL: Documentation, https://docs.jitx.com
Author: JITX
Maintainer: JITX
Keywords: circuit board,jitx,pcb
Classifier: Development Status :: 1 - Planning
Classifier: Framework :: Hatch
Classifier: Framework :: Pytest
Classifier: Intended Audience :: Developers
Classifier: License :: Other/Proprietary License
Classifier: Operating System :: OS Independent
Classifier: Programming Language :: Python
Classifier: Programming Language :: Python :: 3 :: Only
Classifier: Programming Language :: Python :: 3.12
Classifier: Programming Language :: Python :: 3.13
Classifier: Topic :: Scientific/Engineering :: Electronic Design Automation (EDA)
Classifier: Topic :: Software Development :: Libraries :: Python Modules
Classifier: Typing :: Typed
Requires-Python: >=3.12
Requires-Dist: jitx<4.1,>=4.0.0
